{
  "formatVersion": "1.1",
  "component": {
    "group": "com.bcp.bank",
    "module": "gradle-version-catalogs",
    "version": "1.0.1.lts",
    "attributes": {
      "org.gradle.status": "release"
    }
  },
  "createdBy": {
    "gradle": {
      "version": "7.4.2"
    }
  },
  "variants": [
    {
      "name": "versionCatalogElements",
      "attributes": {
        "org.gradle.category": "platform",
        "org.gradle.usage": "version-catalog"
      },
      "files": [
        {
          "name": "gradle-version-catalogs-1.0.1.lts.toml",
          "url": "gradle-version-catalogs-1.0.1.lts.toml",
          "size": 2634,
          "sha512": "4d6159bb11ead75f3215908f8a0eac202cb695d85d845fb127f0d47abbcc7602218906b84e8cc2fba2c9fa470a63718d7004e563335430b2e138f584d181232b",
          "sha256": "8dba7049788e97161afcd959d5dee89cc85982cbbc918f63d72f5761e7c6bc48",
          "sha1": "6cec057d9737b0ab7462a4a4a4b825e81e46ff51",
          "md5": "d428f5ab70c0b11064d283bc2096b2bd"
        }
      ]
    }
  ]
}
