{
  "formatVersion": "1.1",
  "component": {
    "group": "com.bcp.bank",
    "module": "gradle-version-catalogs",
    "version": "1.0.1.lts",
    "attributes": {
      "org.gradle.status": "release"
    }
  },
  "createdBy": {
    "gradle": {
      "version": "7.4.2"
    }
  },
  "variants": [
    {
      "name": "versionCatalogElements",
      "attributes": {
        "org.gradle.category": "platform",
        "org.gradle.usage": "version-catalog"
      },
      "files": [
        {
          "name": "gradle-version-catalogs-1.0.1.lts.toml",
          "url": "gradle-version-catalogs-1.0.1.lts.toml",
          "size": 5760,
          "sha512": "309ec6b69784707020503d0d3ea4d6a0be202759b19179db0c3b1e287b125e0a9c631f8f489386193f93100918faf8a2594221f78fab9ee813bc070f5bf3a225",
          "sha256": "b992e8fa3cad755f016ea6acc63fa55396c04a564a70ed5755da58eb6bb86127",
          "sha1": "72d507f2b9248cac38987dd2adb5361dd3821481",
          "md5": "3e56b4b90d5a8c8d4646c60cfc1e3495"
        }
      ]
    }
  ]
}
